AUTHORS
CHANGES
LICENSE
MANIFEST.in
README
setup.py
scripts/update_table.py
tests/test_codec.py
translitcodec/__init__.py
translitcodec.egg-info/PKG-INFO
translitcodec.egg-info/SOURCES.txt
translitcodec.egg-info/dependency_links.txt
translitcodec.egg-info/top_level.txt
transtab/Makefile
transtab/README
transtab/REFERENCES
transtab/transcomp
transtab/transtab
transtab/transtab.changes
transtab/transtab.missing-MES-2
transtab/transtab.repertoire
transtab/transtab.utf