Metadata-Version: 1.2
Name: translitcodec
Version: 0.5.2
Summary: Unicode to 8-bit charset transliteration codec
Home-page: https://github.com/claudep/translitcodec
Author: Jason Kirtland
Author-email: jek@discorporate.us
License: MIT License
Platform: UNKNOWN
Classifier: Development Status :: 5 - Production/Stable
Classifier: Intended Audience :: Developers
Classifier: License :: OSI Approved :: MIT License
Classifier: Operating System :: OS Independent
Classifier: Programming Language :: Python
Classifier: Programming Language :: Python :: 3
Classifier: Programming Language :: Python :: 3 :: Only
Classifier: Programming Language :: Python :: Implementation :: CPython
Classifier: Topic :: Software Development :: Libraries
Classifier: Topic :: Utilities
Requires-Python: >=3
